{"en_introduction_index.md":"Byqs7-wK","zh_usecase_index.md":"nEyxZFpA","zh_usecase_rvbook_index.md":"mn5AGPaO","zh_usedirection_operationside_index.md":"_G4SGVHY","zh_usedirection_developmentside_index.md":"BptB_ncK","zh_usecase_setupos_index.md":"CUUfLsTS","zh_usedirection_index.md":"D35nRrea","zh_usedirection_developmentside_sources_coremark_index.md":"Bu_uBabH","zh_usedirection_developmentside_environments_index.md":"CDnEBznL","zh_usedirection_developmentside_typeselection_index.md":"4viamjLa","zh_index.md":"rkif4FO1","zh_sdk_gnu_index.md":"Blnd8hAF","zh_sdk_llvm_index.md":"TLHSY938","zh_ruyi_index.md":"JWiZK9tH","zh_introduction_index.md":"DCnbcudc","zh_ruyi_getstarted_index.md":"B5LmHlVk","en_index.md":"C3kr6DQP","zh_ruyi_updates_0.5.0.md":"BD4ZErln","zh_usecase_x86pc_index.md":"ydA4oVhv","zh_ruyi_updates_0.3.0.md":"B-oB5yT_","zh_devices_index.md":"CLe1jvHM","zh_introduction_requirement.md":"UwMhilE-","zh_ruyi_updates_0.6.0.md":"5xwk1eYP","zh_ruyi_updates_0.4.0.md":"CmsSm74O","zh_plan_index.md":"CjJf0tg3"}
